README.md
setup.py
inchwormrf/__init__.py
inchwormrf/helpers.py
inchwormrf/inchworm.py
inchwormrf/inchworm1.py
inchwormrf/inchworm2.py
inchwormrf/inchworm3.py
inchwormrf/inchworm4.py
inchwormrf/inchworm5.py
inchwormrf/inchworm6.py
inchwormrf/inchworm7.py
inchwormrf/inchworm8.py
inchwormrf/inverse_coefs.py
inchwormrf/newton.py
inchwormrf.egg-info/PKG-INFO
inchwormrf.egg-info/SOURCES.txt
inchwormrf.egg-info/dependency_links.txt
inchwormrf.egg-info/requires.txt
inchwormrf.egg-info/top_level.txt