Metadata-Version: 1.0
Name: inchwormrf
Version: 0.0.2
Summary: inchwormrf, a local inversion root finder
Home-page: https://github.com/EFavDB/inchwormrf
Author: Jonathan Landy, YongSeok Jho
Author-email: jslandy@gmail.com
License: MIT
Platform: UNKNOWN
